.travis.yml
LICENSE
MANIFEST.in
README.rst
setup.cfg
setup.py
tox.ini
Mopidy_RNZ.egg-info/PKG-INFO
Mopidy_RNZ.egg-info/SOURCES.txt
Mopidy_RNZ.egg-info/dependency_links.txt
Mopidy_RNZ.egg-info/entry_points.txt
Mopidy_RNZ.egg-info/not-zip-safe
Mopidy_RNZ.egg-info/requires.txt
Mopidy_RNZ.egg-info/top_level.txt
mopidy_rnz/__init__.py
mopidy_rnz/backend.py
mopidy_rnz/content.py
mopidy_rnz/ext.conf
mopidy_rnz/news.py
tests/__init__.py
tests/test_extension.py