Metadata-Version: 1.1
Name: Mopidy-RNZ
Version: 0.1.1
Summary: Mopidy extension for RNZ content
Home-page: https://github.com/danbrough/mopidy-rnz
Author: Dan Brough
Author-email: dan@danbrough.org
License: Apache License, Version 2.0
Platform: UNKNOWN
Classifier: Environment :: No Input/Output (Daemon)
Classifier: Intended Audience :: End Users/Desktop
Classifier: License :: OSI Approved :: Apache Software License
Classifier: Operating System :: OS Independent
Classifier: Programming Language :: Python :: 2
Classifier: Topic :: Multimedia :: Sound/Audio :: Players
